seqpandas/vcf.py
seqpandas/alignment.py
seqpandas/__init__.py
seqpandas/pileup.py
seqpandas/logo.py
seqpandas/cli.py
seqpandas/seqpandas.py
seqpandas/bed.py
seqpandas/tools/__init__.py
seqpandas/tools/pathing.py
seqpandas/cython_numpy/cython_np_array.cpython-312-darwin.so
seqpandas/cython_numpy/__init__.py
seqpandas/colors/custom_glyphs.json
seqpandas-0.1.0.dist-info/RECORD
seqpandas-0.1.0.dist-info/WHEEL
seqpandas-0.1.0.dist-info/entry_points.txt
seqpandas-0.1.0.dist-info/METADATA
